dstricks/__init__.py
dstricks/cfg.py
dstricks/model_metrics.py
dstricks/plot.py
dstricks-0.0.22.dist-info/LICENSE
dstricks-0.0.22.dist-info/METADATA
dstricks-0.0.22.dist-info/WHEEL
dstricks-0.0.22.dist-info/top_level.txt
dstricks-0.0.22.dist-info/RECORD
